NTMpy/NTMpy.py
NTMpy/NTMpy_v0_1_1.py
NTMpy/__init__.py
NTMpy-0.1.1.dist-info/LICENSE.txt
NTMpy-0.1.1.dist-info/METADATA
NTMpy-0.1.1.dist-info/WHEEL
NTMpy-0.1.1.dist-info/top_level.txt
NTMpy-0.1.1.dist-info/RECORD
